cereal/__init__.py
cereal/eat.py
cereal/py.typed
cereal_py-1.0.3.dist-info/LICENSE
cereal_py-1.0.3.dist-info/METADATA
cereal_py-1.0.3.dist-info/WHEEL
cereal_py-1.0.3.dist-info/top_level.txt
cereal_py-1.0.3.dist-info/RECORD
