Metadata-Version: 2.1
Name: cereal-py
Version: 1.0.3
Summary: Create an iterable set of pointers to a specified length. Utilities for working with ZeroIntensity's pointers.py
Author: Joshua Auchincloss
Author-email: <joshua.auchincloss@proton.me>
License: MIT
Project-URL: Source, https://github.com/joshua-auchincloss/cereal
Project-URL: Documentation, https://cereal-py.netlify.app
Keywords: python,cereal,pointers
Classifier: Programming Language :: Python :: 3.8
Classifier: Programming Language :: Python :: 3.9
Classifier: Programming Language :: Python :: 3.10
Classifier: Programming Language :: Python :: 3.11
Classifier: License :: OSI Approved :: MIT License
Classifier: Operating System :: OS Independent
License-File: LICENSE
Requires-Dist: typing-extensions
Requires-Dist: pointers.py
Requires-Dist: psutil
